cafex_db/__init__.py
cafex_db/database_comparator.py
cafex_db/database_handler.py
cafex_db/database_operations.py
cafex_db/databricks_utils.py
cafex_db/db_exceptions.py
cafex_db/db_security.py
cafex_db/mongo_utils.py
cafex_db/snowflake_utils.py
cafex_db-1.0.0.dist-info/METADATA
cafex_db-1.0.0.dist-info/WHEEL
cafex_db-1.0.0.dist-info/top_level.txt
cafex_db-1.0.0.dist-info/RECORD
