Metadata-Version: 2.4
Name: cafex-db
Version: 1.0.0
Summary: DB Library
Author-email: QA Automation Team <qa_automation@gmail.com>
Project-URL: Homepage, https://example.com
Project-URL: Documentation, https://readthedocs.org
Project-URL: Repository, https://github.com/me/spam.git
Project-URL: Issues, https://github.com/me/spam/issues
Project-URL: Changelog, https://github.com/me/spam/blob/master/CHANGELOG.md
Keywords: db,db testing,pytest,automation
Classifier: Programming Language :: Python :: 3
Classifier: Operating System :: OS Independent
Requires-Python: >=3.12
Requires-Dist: cafex-core>=1.0.0
Requires-Dist: thrift==0.16.0
Requires-Dist: PyHive==0.7.0
Requires-Dist: snowflake-connector-python==3.8.1
Requires-Dist: PyMySQL==1.1.1
Requires-Dist: oracledb==3.1.0
Requires-Dist: sqlAlchemy==1.4.29
Requires-Dist: pymssql==2.3.0
Requires-Dist: pysnowflake==0.1.3
Requires-Dist: cassandra-driver==3.29.2
Requires-Dist: pymongo==4.11.2
Requires-Dist: google-cloud-bigquery==3.31.0
Requires-Dist: pymongo==4.11.2
Requires-Dist: psycopg2==2.9.10
